snowconvert/__init__.py
snowconvert/helpers.py
snowconvert_helpers-67454.0.1.dist-info/licenses/LICENSE
snowconvert_helpers-67454.0.1.dist-info/METADATA
snowconvert_helpers-67454.0.1.dist-info/WHEEL
snowconvert_helpers-67454.0.1.dist-info/top_level.txt
snowconvert_helpers-67454.0.1.dist-info/RECORD
