Metadata-Version: 2.4
Name: snowconvert-helpers
Version: 67454.0.1
Summary: Migration helpers for Snowflake SnowConvert for Teradata.
Home-page: https://docs.snowconvert.com/snowconvert/for-teradata/introduction
Author: Snowflake Inc.
Author-email: snowconvert-info@snowflake.com
License: Copyright (c) 2019-2023 Snowflake Inc. All Rights Reserved.
Keywords: Snowflake,Teradata,BTEQ,FastLoad,MultiLoad,TPT,TPump,database,cloud
Classifier: Development Status :: 5 - Production/Stable
Classifier: Environment :: Console
Classifier: License :: Other/Proprietary License
Classifier: Operating System :: OS Independent
Classifier: Programming Language :: Python :: 3.6
Classifier: Programming Language :: Python :: 3.7
Classifier: Programming Language :: Python :: 3.8
Classifier: Programming Language :: SQL
Classifier: Topic :: Database
Classifier: Topic :: Software Development
Classifier: Topic :: Software Development :: Libraries
Classifier: Topic :: Software Development :: Libraries :: Application Frameworks
Classifier: Topic :: Software Development :: Libraries :: Python Modules
Requires-Python: >=3.6
License-File: LICENSE
Requires-Dist: snowflake-connector-python>=2.4.3
Requires-Dist: Deprecated<2.0.0,>=1.2.12
Dynamic: author
Dynamic: author-email
Dynamic: classifier
Dynamic: description
Dynamic: description-content-type
Dynamic: home-page
Dynamic: keywords
Dynamic: license
Dynamic: license-file
Dynamic: requires-dist
Dynamic: requires-python
Dynamic: summary
